README.md
setup.py
Jin_Py.egg-info/PKG-INFO
Jin_Py.egg-info/SOURCES.txt
Jin_Py.egg-info/dependency_links.txt
Jin_Py.egg-info/requires.txt
Jin_Py.egg-info/top_level.txt
jin/__init__.py
jin/cli.py
jin/composer.py
jin/makeconfig.py
jin/parseconfig.py
jin/runner.py
jin/watcher.py
scripts/jin