Metadata-Version: 1.1
Name: Jin-Py
Version: 1.0.31
Summary: A git/mercurial flavored wrapper for rsync.
Home-page: https://github.com/kyoto-shift/jin
Author: Judah Caruso Rodriguez
Author-email: judah@tuta.io
License: MIT
Keywords: jin git mercurial rsync wrapper
Platform: UNKNOWN
Classifier: Development Status :: 4 - Beta
Classifier: Environment :: Console
Classifier: Topic :: Software Development :: Version Control
Classifier: Topic :: Software Development :: Version Control :: Git
Classifier: Topic :: Software Development :: Version Control :: Mercurial
